cpptopy.py
cpptopy-0.0.1.dist-info/METADATA
cpptopy-0.0.1.dist-info/WHEEL
cpptopy-0.0.1.dist-info/top_level.txt
cpptopy-0.0.1.dist-info/RECORD
