Metadata-Version: 2.1
Name: cpptopy
Version: 0.0.1
Summary: Runs a cpp program written as a triplequoted string inside python
Home-page: UNKNOWN
License: UNKNOWN
Platform: UNKNOWN
